stm32bridge/__init__.py
stm32bridge/constants.py
stm32bridge/exceptions.py
stm32bridge/main.py
stm32bridge/cli/__init__.py
stm32bridge/cli/analyze.py
stm32bridge/cli/generate_board.py
stm32bridge/cli/list_boards.py
stm32bridge/cli/migrate.py
stm32bridge/core/__init__.py
stm32bridge/core/analyzer.py
stm32bridge/core/generator.py
stm32bridge/core/migrator.py
stm32bridge/utils/__init__.py
stm32bridge/utils/board_generator.py
stm32bridge/utils/boards.py
stm32bridge/utils/build.py
stm32bridge/utils/editor.py
stm32bridge/utils/mcu_scraper.py
stm32bridge/utils/platformio.py
stm32bridge-1.3.3.dist-info/licenses/LICENSE
stm32bridge-1.3.3.dist-info/METADATA
stm32bridge-1.3.3.dist-info/WHEEL
stm32bridge-1.3.3.dist-info/entry_points.txt
stm32bridge-1.3.3.dist-info/top_level.txt
stm32bridge-1.3.3.dist-info/RECORD
