Metadata-Version: 2.4
Name: stm32bridge
Version: 1.3.3
Summary: STM32CubeMX to PlatformIO Migration Tool
Home-page: https://github.com/yourusername/stm32bridge
Author: STM32Bridge Team
Author-email: STM32Bridge Team <dev@stm32bridge.com>
Project-URL: Homepage, https://github.com/yourusername/stm32bridge
Project-URL: Bug Reports, https://github.com/yourusername/stm32bridge/issues
Project-URL: Source Code, https://github.com/yourusername/stm32bridge
Project-URL: Documentation, https://github.com/yourusername/stm32bridge/blob/main/README.md
Keywords: stm32,cubemx,platformio,embedded,migration,freertos,arm,cortex,microcontroller,iot
Classifier: Development Status :: 4 - Beta
Classifier: Intended Audience :: Developers
Classifier: Topic :: Software Development :: Embedded Systems
Classifier: Topic :: Software Development :: Code Generators
Classifier: License :: OSI Approved :: MIT License
Classifier: Programming Language :: Python :: 3
Classifier: Programming Language :: Python :: 3.8
Classifier: Programming Language :: Python :: 3.9
Classifier: Programming Language :: Python :: 3.10
Classifier: Programming Language :: Python :: 3.11
Classifier: Programming Language :: Python :: 3.12
Classifier: Operating System :: OS Independent
Classifier: Environment :: Console
Requires-Python: >=3.8
License-File: LICENSE
Requires-Dist: typer>=0.9.0
Requires-Dist: rich>=13.0.0
Requires-Dist: requests>=2.28.0
Requires-Dist: beautifulsoup4>=4.11.0
Provides-Extra: dev
Requires-Dist: pytest>=6.0; extra == "dev"
Requires-Dist: black>=22.0; extra == "dev"
Requires-Dist: flake8>=4.0; extra == "dev"
Requires-Dist: mypy>=0.900; extra == "dev"
Provides-Extra: test
Requires-Dist: pytest>=7.0.0; extra == "test"
Requires-Dist: pytest-cov>=4.0.0; extra == "test"
Requires-Dist: pytest-mock>=3.10.0; extra == "test"
Requires-Dist: pytest-asyncio>=0.21.0; extra == "test"
Requires-Dist: responses>=0.23.0; extra == "test"
Requires-Dist: factory-boy>=3.2.0; extra == "test"
Provides-Extra: build
Requires-Dist: GitPython>=3.1.0; extra == "build"
Provides-Extra: pdf
Requires-Dist: PyPDF2>=3.0.0; extra == "pdf"
Requires-Dist: pdfplumber>=0.7.0; extra == "pdf"
Dynamic: author
Dynamic: home-page
Dynamic: license-file
Dynamic: requires-python
